dnf-plugins/__init__.py
dnf-plugins/tracer_upload.py
katello/__init__.py
katello/constants.py
katello/enabled_report.py
katello/packages.py
katello/repos.py
katello/scripts.py
katello/uep.py
katello/utils.py
katello/contrib/etc/rhsm/pluginconf.d/fqdn.FactsPlugin.conf
katello/contrib/etc/yum/pluginconf.d/enabled_repos_upload.conf
katello/contrib/etc/yum/pluginconf.d/package_upload.conf
katello/contrib/etc/yum/pluginconf.d/tracer_upload.conf
katello/contrib/extra/81-tracer-upload-apt
katello/contrib/extra/katello-tracer-upload-dnf
katello/contrib/extra/katello-tracer-upload.cron
katello/tracer/SystemdDbus.py
katello/tracer/__init__.py
katello/tracer/deb.py
katello/tracer/dnf.py
katello/tracer/zypper.py
yum-plugins/__init__.py
yum-plugins/enabled_repos_upload.py
yum-plugins/package_upload.py
yum-plugins/tracer_upload.py
zypper_plugins/__init__.py
zypper_plugins/enabled_repos_upload.py
zypper_plugins/package_upload.py
zypper_plugins/tracer_upload.py
katello_host_tools-4.5.0.dist-info/METADATA
katello_host_tools-4.5.0.dist-info/WHEEL
katello_host_tools-4.5.0.dist-info/entry_points.txt
katello_host_tools-4.5.0.dist-info/top_level.txt
katello_host_tools-4.5.0.dist-info/RECORD
