Metadata-Version: 2.1
Name: katello-host-tools
Version: 4.5.0
Summary: Libraries and command-line utilities for keeping Katello clients in sync and up to date
Home-page: https://github.com/Katello/katello-host-tools
Author: The Foreman Project
Author-email: no-email@theforeman.org
License: GPLv2+
Platform: UNKNOWN
Classifier: License :: OSI Approved :: GNU General Public License (GPL)
Classifier: Programming Language :: Python
Classifier: Operating System :: POSIX
Classifier: Topic :: Software Development :: Libraries :: Python Modules
